scary/__init__.py
scary-0.1.dist-info/METADATA
scary-0.1.dist-info/RECORD
scary-0.1.dist-info/WHEEL
scary-0.1.dist-info/top_level.txt
