Metadata-Version: 1.0
Name: scary
Version: 0.1
Summary: What if something breaks
Home-page: http://github.com/gauravmhkd25/scary
Author: Flying Circus
Author-email: gauravmhkd25@gmail.com
License: MIT
Platform: UNKNOWN
